{
  "march": {
    "source": "https://www.gov.uk/government/publications/south-east-training-estate-firing-times/aldershot-training-area-closure-times-march-2024",
    "times": {
      "1": {
        "openStatus": "\nClosed   to public   (8am to 4.30pm)",
        "audience": ""
      },
      "2": {
        "openStatus": "Open   to public",
        "audience": ""
      },
      "3": {
        "openStatus": "Open   to public",
        "audience": ""
      },
      "4": {
        "openStatus": "\nClosed   to public   (8am to 4.30pm)",
        "audience": ""
      },
      "5": {
        "openStatus": "\nClosed   to public   (8am to 4.30pm)",
        "audience": ""
      },
      "6": {
        "openStatus": "Closed   to public",
        "audience": ""
      },
      "7": {
        "openStatus": "Closed   to public",
        "audience": ""
      },
      "8": {
        "openStatus": "Closed   to public",
        "audience": ""
      },
      "9": {
        "openStatus": "Open   to public",
        "audience": ""
      },
      "10": {
        "openStatus": "Open   to public",
        "audience": ""
      },
      "11": {
        "openStatus": "\nClosed   to public   (8am to 4.30pm)",
        "audience": ""
      },
      "12": {
        "openStatus": "\nClosed   to public   (8am to 4.30pm)",
        "audience": ""
      },
      "13": {
        "openStatus": "\nClosed   to public   (8am to 4.30pm)",
        "audience": ""
      },
      "14": {
        "openStatus": "\nClosed   to public   (8am to 4.30pm)",
        "audience": ""
      },
      "15": {
        "openStatus": "\nClosed   to public   (8am to 4.30pm)",
        "audience": ""
      },
      "16": {
        "openStatus": "Open   to public",
        "audience": ""
      },
      "17": {
        "openStatus": "Open   to public",
        "audience": ""
      },
      "18": {
        "openStatus": "\nClosed   to public   (8am to 4.30pm)",
        "audience": ""
      },
      "19": {
        "openStatus": "\nClosed   to public   (8am to 4.30pm)",
        "audience": ""
      },
      "20": {
        "openStatus": "\nClosed   to public   (8am to 4.30pm)",
        "audience": ""
      },
      "21": {
        "openStatus": "\nClosed   to public   (8am to 4.30pm)",
        "audience": ""
      },
      "22": {
        "openStatus": "\nClosed   to public   (8am to 4.30pm)",
        "audience": ""
      },
      "23": {
        "openStatus": "Open   to public",
        "audience": ""
      },
      "24": {
        "openStatus": "Open   to public",
        "audience": ""
      },
      "25": {
        "openStatus": "\nClosed   to public   (from 8am)",
        "audience": ""
      },
      "26": {
        "openStatus": "\nClosed   to public   (Day & Night training)",
        "audience": ""
      },
      "27": {
        "openStatus": "\nClosed   to public   (Day & Night training)",
        "audience": ""
      },
      "28": {
        "openStatus": "\nClosed   to public   (Day & Night training)",
        "audience": ""
      },
      "29": {
        "openStatus": "\nClosed   to public   (until 4.30pm)",
        "audience": ""
      },
      "30": {
        "openStatus": "Open   to public",
        "audience": ""
      },
      "31": {
        "openStatus": "Open   to public",
        "audience": ""
      }
    }
  },
  "april": {
    "source": "https://www.gov.uk/government/publications/south-east-training-estate-firing-times/aldershot-training-area-closure-times-april-2024",
    "times": {
      "1": {
        "openStatus": "Open   to public",
        "audience": ""
      },
      "2": {
        "openStatus": "\nClosed   to public   (from 8am, Day and Night training)",
        "audience": ""
      },
      "3": {
        "openStatus": "\nClosed   to public   (Day & Night training)",
        "audience": ""
      },
      "4": {
        "openStatus": "\nClosed   to public   (Day & Night training)",
        "audience": ""
      },
      "5": {
        "openStatus": "\nClosed   to public   (until 4.30pm)",
        "audience": ""
      },
      "6": {
        "openStatus": "Open   to public",
        "audience": ""
      },
      "7": {
        "openStatus": "Open   to public",
        "audience": ""
      },
      "8": {
        "openStatus": "\nClosed   to public   (8am to 4.30pm)",
        "audience": ""
      },
      "9": {
        "openStatus": "\nClosed   to public   (8am to 4.30pm)",
        "audience": ""
      },
      "10": {
        "openStatus": "\nClosed   to public   (from 8am, Day and Night training)",
        "audience": ""
      },
      "11": {
        "openStatus": "\nClosed   to public   (until 4.30pm)",
        "audience": ""
      },
      "12": {
        "openStatus": "\nClosed   to public   (8am to 4.30pm)",
        "audience": ""
      },
      "13": {
        "openStatus": "Open   to public",
        "audience": ""
      },
      "14": {
        "openStatus": "Open   to public",
        "audience": ""
      },
      "15": {
        "openStatus": "\nClosed   to public   (8am to 4.30pm)",
        "audience": ""
      },
      "16": {
        "openStatus": "\nClosed   to public   (8am to 4.30pm)",
        "audience": ""
      },
      "17": {
        "openStatus": "\nClosed   to public   (from 8am, Day and Night training)",
        "audience": ""
      },
      "18": {
        "openStatus": "\nClosed   to public   (until 4.30pm)",
        "audience": ""
      },
      "19": {
        "openStatus": "\nClosed   to public   (from 8am, Day and Night training)",
        "audience": ""
      },
      "20": {
        "openStatus": "\nClosed   to public   (Day & Night training)",
        "audience": ""
      },
      "21": {
        "openStatus": "\nClosed   to public   (until 2pm)",
        "audience": ""
      },
      "22": {
        "openStatus": "\nClosed   to public   (8am to 4.30pm)",
        "audience": ""
      },
      "23": {
        "openStatus": "\nClosed   to public   (8am to 4.30pm)",
        "audience": ""
      },
      "24": {
        "openStatus": "\nClosed   to public   (8am to 4.30pm)",
        "audience": ""
      },
      "25": {
        "openStatus": "\nClosed   to public   (8am to 4.30pm)",
        "audience": ""
      },
      "26": {
        "openStatus": "\nClosed   to public   (8am to 4.30pm)",
        "audience": ""
      },
      "27": {
        "openStatus": "Open   to public",
        "audience": ""
      },
      "28": {
        "openStatus": "Open   to public",
        "audience": ""
      },
      "29": {
        "openStatus": "\nClosed   to public   (8am to 4.30pm)",
        "audience": ""
      },
      "30": {
        "openStatus": "\nClosed   to public   (8am to 4.30pm)",
        "audience": ""
      }
    }
  }
}